flet_assets/__init__.py
flet_assets/server.py
flet_assets-0.2.1.dist-info/METADATA
flet_assets-0.2.1.dist-info/WHEEL
flet_assets-0.2.1.dist-info/RECORD
