Metadata-Version: 2.4
Name: flet-assets
Version: 0.2.1
Summary: A lightweight static file server for Flet apps, designed to simplify mobile debugging by serving assets over a local network.
Project-URL: Homepage, https://github.com/nubeDeCalor/flet-staticserver
Project-URL: Bug Tracker, https://github.com/nubeDeCalor/flet-staticserver/issues
Author-email: Julian Perez <mordecaaii@gmail.com>
Classifier: License :: OSI Approved :: MIT License
Classifier: Operating System :: OS Independent
Classifier: Programming Language :: Python :: 3
Requires-Python: >=3.7
Requires-Dist: colorama>=0.4.4
Requires-Dist: fastapi>=0.68.0
Requires-Dist: uvicorn>=0.15.0
